dvc_cc/__init__.py
dvc_cc/__main__.py
dvc_cc/bcolors.py
dvc_cc/cancel/__init__.py
dvc_cc/cancel/__main__.py
dvc_cc/cancel/main.py
dvc_cc/cli_modes.py
dvc_cc/dvc/__init__.py
dvc_cc/dvc/__main__.py
dvc_cc/dvc/main.py
dvc_cc/git/__init__.py
dvc_cc/git/__main__.py
dvc_cc/git/main.py
dvc_cc/hyperopt/__init__.py
dvc_cc/hyperopt/__main__.py
dvc_cc/hyperopt/command.py
dvc_cc/hyperopt/hyperoptimizer.py
dvc_cc/hyperopt/main.py
dvc_cc/hyperopt/new.py
dvc_cc/hyperopt/new_suggest.py
dvc_cc/hyperopt/plot_beta_distribution.py
dvc_cc/hyperopt/stage.py
dvc_cc/hyperopt/var.py
dvc_cc/hyperopt/variable.py
dvc_cc/init/__init__.py
dvc_cc/init/__main__.py
dvc_cc/init/main.py
dvc_cc/keyring/__init__.py
dvc_cc/keyring/__main__.py
dvc_cc/keyring/main.py
dvc_cc/live_output/__init__.py
dvc_cc/live_output/__main__.py
dvc_cc/live_output/main.py
dvc_cc/main.py
dvc_cc/output_to_tmp/__init__.py
dvc_cc/output_to_tmp/__main__.py
dvc_cc/output_to_tmp/main.py
dvc_cc/output_to_tmp/main2.py
dvc_cc/output_to_tmp_old/__init__.py
dvc_cc/output_to_tmp_old/__main__.py
dvc_cc/output_to_tmp_old/main.py
dvc_cc/run/__init__.py
dvc_cc/run/__main__.py
dvc_cc/run/helper.py
dvc_cc/run/jupyter_notebook_to_source.py
dvc_cc/run/main.py
dvc_cc/run/optuna_scripts.py
dvc_cc/run/papermill_helper.py
dvc_cc/run_all_defined/__init__.py
dvc_cc/run_all_defined/__main__.py
dvc_cc/run_all_defined/main.py
dvc_cc/setting/__init__.py
dvc_cc/setting/__main__.py
dvc_cc/setting/config_parser.py
dvc_cc/setting/main.py
dvc_cc/setting/settingsinfo.yml
dvc_cc/sshfs/__init__.py
dvc_cc/sshfs/__main__.py
dvc_cc/sshfs/main.py
dvc_cc/status/__init__.py
dvc_cc/status/__main__.py
dvc_cc/status/main.py
dvc_cc/version.py
dvc_cc-0.10.30.dist-info/entry_points.txt
dvc_cc-0.10.30.dist-info/LICENSE
dvc_cc-0.10.30.dist-info/WHEEL
dvc_cc-0.10.30.dist-info/METADATA
dvc_cc-0.10.30.dist-info/RECORD
