Metadata-Version: 2.1
Name: dvc-cc
Version: 0.10.30
Summary: This connector is used to combine the work of CC (www.curious-containers.cc) and DVC (Open-source Version Control System for Machine Learning Projects).
Home-page: https://github.com/mastaer/dvc-cc.git
License: AGPL-3.0
Author: Jonas Annuscheit
Author-email: annusch@htw-berlin.de
Requires-Python: >=3.6,<4.0
Classifier: License :: OSI Approved :: GNU Affero General Public License v3
Classifier: Programming Language :: Python :: 3
Classifier: Programming Language :: Python :: 3.6
Classifier: Programming Language :: Python :: 3.7
Classifier: Programming Language :: Python :: 3.8
Requires-Dist: cc-faice (>=9,<10)
Requires-Dist: dvc (>=0,<1)
Requires-Dist: keyring (>=19.0,<20.0)
Requires-Dist: matplotlib (>=3.1,<4.0)
Requires-Dist: nbconvert (>=5.5,<6.0)
Requires-Dist: numpy (>=1.16,<2.0)
Requires-Dist: pandas (>=0,<1)
Requires-Dist: paramiko (>=2.4,<3.0)
Requires-Dist: pexpect (>=4.8,<5.0)
Requires-Dist: pyrsistent (>=0.15.2,<0.16.0)
Requires-Dist: python-gitlab (>=1.8,<2.0)
Requires-Dist: pyyaml (>=5.1,<6.0)
Requires-Dist: seaborn (>=0,<1)
Project-URL: Repository, https://github.com/mastaer/dvc-cc.git
